{
  "id": "playstation",
  "schema_version": "0.3",
  "url": "https://www.playstation.com",
  "title": "Playstation",
  "image": "https://image.thum.io/get/width/1440/https://www.playstation.com",
  "tags": [
    "Product",
    "Consumer",
    "Dark Mode",
    "Motion",
    "Playful"
  ],
  "status": "failed:JSONDecodeError",
  "added_at": "2026-05-29",
  "added_by": "ingest",
  "_meta": {
    "vision_model": "mimo-v2.5",
    "vision_prompt_version": "0.3",
    "vision_at": "2026-05-28T21:42:33+00:00",
    "vision_tokens": 3277,
    "vision_cost_usd": 0.0364,
    "last_error": "Invalid control character at: line 75 column 14 (char 1876)"
  },
  "spec": {
    "colors": {
      "bg": "#000000",
      "bgSoft": null,
      "bgQuiet": "#FFFFFF",
      "ink": "#FFFFFF",
      "inkSoft": null,
      "muted": "#666666",
      "mutedSoft": null,
      "accent": "#E55C00",
      "line": "rgba(0, 0, 0, 0.1)"
    },
    "typography": {
      "display": "geometric-sans",
      "body": "humanist-sans",
      "mono": null,
      "scale": [
        {
          "token": "display",
          "size": 48,
          "lh": 1.1,
          "weight": 700,
          "ls": "-1px"
        },
        {
          "token": "heading",
          "size": 32,
          "lh": 1.2,
          "weight": 400,
          "ls": "-0.5px"
        },
        {
          "token": "body",
          "size": 16,
          "lh": 1.5,
          "weight": 400,
          "ls": "0px"
        }
      ]
    },
    "spacing": {
      "base": 4,
      "scale": [
        4,
        8,
        16,
        24,
        32,
        48,
        64,
        96
      ]
    },
    "surfaces": {
      "radius": {
        "sm": 4,
        "md": 8,
        "lg": 12,
        "pill": 999
      }
    },
    "layout": {
      "container": 1440,
      "paragraph": 680,
      "columns": 12,
      "gutter": 24,
      "breakpoints": [
        768,
        1024
      ]
    },
    "motion": {
      "durations": {
        "micro": 220,
        "small": 400,
        "medium": 800
      },
      "easing": "cubic-bezier(0.4, 0.0, 0.2, 1)"
    }
  },
  "spec_i18n": {
    "en": {
      "identity": {
        "keywords": [
          "gaming",
          "entertainment",
          "console",
          "hardware",
          "digital"
        ],
        "analogy": "A vibrant, high-energy digital entertainment storefront",
        "oneLiner": "A bold, immersive consumer gaming platform hub."
      },
      "colors": {
        "principle": "High contrast with vibrant, saturated accents on dark or clean white backgrounds."
      },
      "typography": {
        "rules": [
          "Use bold weights for primary headings.",
          "Keep line length moderate for readability."
        ],
        "scaleUses": [
          "Hero headlines",
          "Section headlines",
          "Body text"
        ]
      },
      "spacing": {
        "rhythm": "Generous vertical spacing creates breathing room between sections."
      },
      "surfaces": {
        "shadows": [
          "0 4px 12px rgba(0,0,0,0.1)"
        ],
        "borders": "Subtle or no borders; relies on color contrast for separation."
      },
      "layout": {
        "skeleton": "Full-width hero sections with centered or left-aligned content."
      },
      "components": {
        "button": "Solid, rounded pill-shaped buttons with high contrast.",
        "card": "Product thumbnails or promotional blocks.",
        "chip": null,
        "input": null,
        "hero": "Full-width, vibrant gradient with floating 3D shapes."
      },
      "motion": {
        "patterns": [
          "Subtle hover effects on interactive elements."
        ]
      },
      "interaction": {
        "hover": "Subtle color shift or scale increase.",
        "click": "Immediate visual feedback.",
        "transition": "Smooth state changes.",
        "keyboard": "Standard focus outlines."
      },
      "voice": {
        "tone": "Enthusiastic, inviting, and direct.",
        "headlineStyle": "Bold, action-oriented statements.",
        "ctaStyle": "Imperative verbs (Shop, Discover, Find out more).",
        "avoid": [
          "Overly technical jargon",
          "Passive language",
          "Cluttered text"
        ]
      },
      "donts": [
        "Don't use muted pastel palettes — screenshot shows vibrant blues, oranges, and greens.",
        "Don't use thin, delicate typography — screenshot shows bold, geometric sans-serif headlines.",
        "Don't use complex grid layouts with many columns — screenshot uses large, clear sections.",
        "Don't use realistic photography as the primary hero element — screenshot uses stylized 3D graphics.",
        "Don't use subtle, barely-visible interactive states — screenshot uses high-contrast buttons.",
        "Don't use small, cramped spacing — screenshot uses generous whitespace."
      ],
      "systemPrompt": "This is a bold, high-energy consumer gaming platform (PlayStation). The palette is anchored by deep blacks (#000000) and clean whites (#FFFFFF), with a vibrant, high-chroma orange accent (#E55C00). Typography relies on geometric sans-serif for display and humanist sans-serif for body. The layout is a full-width, immersive experience with large hero sections. Critical donts: avoid muted pastels, avoid thin delicate typography, avoid cluttered grids, avoid realistic photography as the main hero element, avoid subtle interactive states, and avoid cramped spacing."
    },
    "zh-CN": {
      "identity": {
        "keywords": [
          "游戏",
          "娱乐",
          "主机",
          "硬件",
          "数字"
        ],
        "analogy": "一个充满活力、高能量的数字娱乐商店",
        "oneLiner": "一个大胆、沉浸式的消费级游戏平台中心。"
      },
      "colors": {
        "principle": "在深色或纯净白色背景上，采用高对比度搭配鲜艳、饱和的点缀色。"
      },
      "typography": {
        "rules": [
          "主要标题使用粗体字重。",
          "保持适中的行宽以利于阅读。"
        ],
        "scaleUses": [
          "首屏大标题",
          "板块标题",
          "正文"
        ]
      },
      "spacing": {
        "rhythm": "充裕的垂直间距在各板块间创造了呼吸空间。"
      },
      "surfaces": {
        "shadows": [
          "0 4px 12px rgba(0,0,0,0.1)"
        ],
        "borders": "边框极简或无边框；依赖颜色对比实现视觉分隔。"
      },
      "layout": {
        "skeleton": "全宽首屏区域，内容居中或左对齐。"
      },
      "components": {
        "button": "纯色、圆角的胶囊形按钮，高对比度。",
        "card": "产品缩略图或宣传区块。",
        "chip": null,
        "input": null,
        "hero": "全宽、色彩鲜艳的渐变背景，配以浮动的3D形状。"
      },
      "motion": {
        "patterns": [
          "交互元素上细腻的hover效果。"
        ]
      },
      "interaction": {
        "hover": "细微的颜色变化或尺寸放大。",
        "click": "即时的视觉反馈。",
        "transition": "流畅的状态切换。",
        "keyboard": "标准的focus轮廓。"
      },
      "voice": {
        "tone": "热情、友好且直接。",
        "headlineStyle": "大胆、行动导向的陈述。",
        "ctaStyle": "祈使句动词（购买、探索、了解更多）。",
        "avoid": [
          "过于技术化的术语",
          "被动语态",
          "杂乱的文字"
        ]
      },
      "donts": [
        "避免使用柔和的粉彩色调——截图显示的是鲜艳的蓝色、橙色和绿色。",
        "避免使用纤细、精致的字体——截图显示的是粗体、几何无衬线标题字体。",
        "避免使用多列的复杂网格布局——截图使用的是大而清晰的板块。",
        "避免使用写实摄影作为主要的首屏元素——截图使用的是风格化的3D图形。",
        "避免使用细微、几乎不可见的交互状态——截图使用的是高对比度按钮。",
        "避免使用狭小、拥挤的间距——截图使用的是充裕的留白。"
      ],
      "systemPrompt": "这是一个大胆、高能量的消费级游戏平台（PlayStation）。配色以深黑色（#000000）和纯净白色（#FFFFFF）为基础，搭配一个鲜艳、高饱和度的橙色点缀色（#E55C00）。字体在展示层使用几何无衬线体，在正文层使用人文主义无衬线体。布局是全宽、沉浸式的体验，包含大型首屏区域。关键禁忌：避免柔和粉彩、避免纤细精致的字体、避免杂乱的网格、避免将写实摄影作为主要首屏元素、避免细微的交互状态，以及避免拥挤的间距。"
    },
    "zh-TW": {
      "identity": {
        "keywords": [
          "遊戲",
          "娛樂",
          "主機",
          "硬體",
          "數位"
        ],
        "analogy": "一個充滿活力、高能量的數位娛樂店面",
        "oneLiner": "一個大膽、沉浸式的消費遊戲平台樞紐。"
      },
      "colors": {
        "principle": "在深色或乾淨的白色背景上，使用高對比並搭配鮮活、飽和的強調色。"
      },
      "typography": {
        "rules": [
          "主要標題使用粗體字重。",
          "保持適中的行長以利閱讀。"
        ],
        "scaleUses": [
          "主視覺標題",
          "區塊標題",
          "內文"
        ]
      },
      "spacing": {
        "rhythm": "寬裕的垂直間距為區塊間創造呼吸空間。"
      },
      "surfaces": {
        "shadows": [
          "0 4px 12px rgba(0,0,0,0.1)"
        ],
        "borders": "邊框微妙或無邊框；依賴色彩對比來區隔。"
      },
      "layout": {
        "skeleton": "全寬主視覺區塊，內容置中或靠左對齊。"
      },
      "components": {
        "button": "實心、圓角藥丸形按鈕，具高對比度。",
        "card": "產品縮圖或宣傳區塊。",
        "chip": null,
        "input": null,
        "hero": "全寬、鮮活的漸層背景，搭配浮動的 3D 造型。"
      },
      "motion": {
        "patterns": [
          "互動元素帶有細微的 hover 效果。"
        ]
      },
      "interaction": {
        "hover": "微妙的色彩變化或縮放增大。",
        "click": "立即的視覺回饋。",
        "transition": "平滑的狀態變化。",
        "keyboard": "標準的 focus 外框。"
      },
      "voice": {
        "tone": "熱情、有吸引力且直接。",
        "headlineStyle": "大膽、行動導向的陳述。",
        "ctaStyle": "祈使動詞（購買、探索、了解更多）。",
        "avoid": [
          "過度專業的術語",
          "被動語態",
          "雜亂的文字"
        ]
      },
      "donts": [
        "不要使用柔和的粉彩色調——截圖顯示鮮活的藍色、橘色與綠色。",
        "不要使用纖細、精緻的字體——截圖顯示粗體、幾何風格的無襯線標題。",
        "不要使用複雜的多欄網格佈局——截圖使用大而清晰的區塊。",
        "不要使用寫實攝影作為主要的主視覺元素——截圖使用風格化的 3D 圖形。",
        "不要使用細微、幾乎看不見的互動狀態——截圖使用高對比度按鈕。",
        "不要使用狹窄、擁擠的間距——截圖使用寬裕的留白。"
      ],
      "systemPrompt": "這是一個大膽、高能量的消費遊戲平台（PlayStation）。色彩基調以深黑色（#000000）和乾淨的白色（#FFFFFF）為主，搭配鮮活、高彩度的橘色強調色（#E55C00）。字體採用幾何無襯線體作為標題，人文無襯線體作為內文。佈局是全寬、沉浸式的體驗，具有大型主視覺區塊。關鍵禁忌：避免使用柔和粉彩、避免使用纖細精緻的字體、避免使用擁擠的網格、避免使用寫實攝影作為主要主視覺、避免使用細微的互動狀態，以及避免使用狹窄的間距。"
    }
  },
  "desc": {
    "en": {
      "palette": "High-contrast blacks and whites punctuated by a vibrant orange accent and colorful 3D promotional graphics.",
      "layout": "Full-width, sectioned layout designed for immersive, large-scale visual content.",
      "interaction": "Clean, high-contrast buttons with straightforward hover states.",
      "motion": "Implied subtle animations in the floating 3D elements of the hero section.",
      "notes": "A prime example of high-energy consumer branding with a strong emphasis on vibrant visual graphics."
    },
    "zh-CN": {
      "palette": "高对比度的黑白基调，辅以鲜明的橙色点缀和多彩的3D宣传图形。",
      "layout": "全宽分段式布局，为沉浸式、大规模视觉内容而设计。",
      "interaction": "简洁、高对比度的按钮，具备直观的hover状态。",
      "motion": "首屏浮动3D元素蕴含着细腻的动效。",
      "notes": "高能量消费品牌设计的典范，极度强调生动的视觉图形。"
    },
    "zh-TW": {
      "palette": "高對比的黑白色調，點綴著鮮活的橘色強調色與多彩的 3D 宣傳圖形。",
      "layout": "全寬、分區式佈局，專為大規模沉浸式視覺內容而設計。",
      "interaction": "簡潔、高對比的按鈕，配以直覺的 hover 狀態。",
      "motion": "主視覺區塊中浮動的 3D 元素隱含著細膩的動畫。",
      "notes": "一個充滿活力的消費品牌範例，強烈強調鮮活的視覺圖形。"
    }
  }
}
